findpydeps/__init__.py
findpydeps/__main__.py
findpydeps/findpydeps.py
findpydeps-0.2.8.dist-info/licenses/LICENSE
findpydeps-0.2.8.dist-info/METADATA
findpydeps-0.2.8.dist-info/WHEEL
findpydeps-0.2.8.dist-info/entry_points.txt
findpydeps-0.2.8.dist-info/top_level.txt
findpydeps-0.2.8.dist-info/RECORD
