Metadata-Version: 2.4
Name: findpydeps
Version: 0.2.8
Summary: Find the python dependencies used by your python files and projects
Home-page: https://github.com/Nicolas-Reyland/findpydeps
Author: Nicolas Reyland
Author-email: nicolas@reyland.dev
Maintainer: Nicolas Reyland
Maintainer-email: nicolas@reyland.dev
License: MIT License
Project-URL: Bug Tracker, https://github.com/Nicolas-Reyland/findpydeps/issues
Classifier: Development Status :: 4 - Beta
Classifier: Programming Language :: Python :: 3
Classifier: Environment :: Console
Classifier: License :: OSI Approved :: MIT License
Classifier: Operating System :: OS Independent
Classifier: Intended Audience :: Developers
Classifier: Topic :: Software Development :: Libraries :: Python Modules
Classifier: Natural Language :: English
Requires-Python: >=3.8
License-File: LICENSE
Dynamic: license-file
